Workbook

Sheet CATALOGO_MOTOS
C2: LISTA DE PRECIOS | I2: MANO DE OBRA GRATIS EN 2° SERVICIO
B4: Clave | C4: Modelo | D4: Precio Lista | E4: Precio Contado | G4: 3 Meses
B5: SCOOTER
A6: 1 | C6: X MAX TECH MAX | D6: 178947 | E6: 169999 | F6: =D6*3% -> 5368.41 | G6: =D6-F6 -> 173578.59 | J6: =D6*5% -> 8947.35 | K6: =D6-J6 -> 169999.65 | L6: MOTONETA X MAX TECH MAX (2026)
F7: =D7*3% -> 0 | G7: =D7-F7 -> 0 | J7: =D7*5% -> 0 | K7: =D7-J7 -> 0
A8: 2 | B8: CZD300BS | C8: X MAX (2025) | D8: 170526 | E8: 161999 | F8: =D8*3% -> 5115.78 | G8: =D8-F8 -> 165410.22 | J8: =D8*5% -> 8526.3 | K8: =D8-J8 -> 161999.7 | L8: MOTONETA X MAX (2025)
A10: 3 | B10: CZD300BT | C10: X MAX (2026) | D10: 172631 | E10: 163999 | F10: =D10*3% -> 5178.93 | G10: =D10-F10 -> 167452.07 | J10: =D10*5% -> 8631.55 | K10: =D10-J10 -> 163999.45 | L10: MOTONETA X MAX (2026)
F11: =D11*3% -> 0 | G11: =D11-F11 -> 0 | J11: =D11*5% -> 0 | K11: =D11-J11 -> 0
A12: 4 | B12: LCX125BS | C12: FASCINO | D12: 49473 | E12: 46999 | F12: =D12*3% -> 1484.19 | G12: =D12-F12 -> 47988.81 | J12: =D12*5% -> 2473.65 | K12: =D12-J12 -> 46999.35 | L12: MOTONETA FASCINO (2025) | M12: CON BONO 2,000.00 | O12: 44999
F13: =D13*3% -> 0 | G13: =D13-F13 -> 0 | J13: =D13*5% -> 0 | K13: =D13-J13 -> 0
A14: 5 | B14: XP560DZ4 | C14: T-MAX (2025) | D14: 385262 | E14: 365999 | F14: =D14*3% -> 11557.86 | G14: =D14-F14 -> 373704.14 | J14: =D14*5% -> 19263.1 | K14: =D14-J14 -> 365998.9 | L14: MOTONETA T-MAX (2025)
A16: 6 | B16: XP560 | C16: T-MAX (2026) | D16: 387368 | E16: 367999 | F16: =D16*3% -> 11621.04 | G16: =D16-F16 -> 375746.96 | J16: =D16*5% -> 19368.4 | K16: =D16-J16 -> 367999.6 | L16: MOTONETA T-MAX (2026)
A18: 7 | B18: GPD155BS | C18: N-MAX (2025) | D18: 104736 | E18: 99499 | F18: =D18*3% -> 3142.08 | G18: =D18-F18 -> 101593.92 | J18: =D18*5% -> 5236.8 | K18: =D18-J18 -> 99499.2 | L18: MOTONETA N-MAX (2025)
F19: =D19*3% -> 0 | G19: =D19-F19 -> 0 | J19: =D19*5% -> 0 | K19: =D19-J19 -> 0
A20: 8 | B20: GPD155Bt | C20: N-MAX (2026) | D20: 105262 | E20: 99999 | F20: =D20*3% -> 3157.86 | G20: =D20-F20 -> 102104.14 | J20: =D20*5% -> 5263.1 | K20: =D20-J20 -> 99998.9 | L20: MOTONETA N-MAX (2026)
F21: =D21*3% -> 0 | G21: =D21-F21 -> 0 | J21: =D21*5% -> 0 | K21: =D21-J21 -> 0
A22: 9 | B22: LCG125BS | C22: RAY ZR 125 (2025) | D22: 57367 | E22: 54499 | F22: =D22*3% -> 1721.01 | G22: =D22-F22 -> 55645.99 | J22: =D22*5% -> 2868.35 | K22: =D22-J22 -> 54498.65 | L22: MOTONETA RAY ZR 125 (2025)
F23: =D23*3% -> 0 | G23: =D23-F23 -> 0 | J23: =D23*5% -> 0 | K23: =D23-J23 -> 0
A24: 10 | B24: LCG125BT | C24: RAY ZR 125 (2026) | D24: 57894 | E24: 54999 | F24: =D24*3% -> 1736.82 | G24: =D24-F24 -> 56157.18 | J24: =D24*5% -> 2894.7 | K24: =D24-J24 -> 54999.3 | L24: MOTONETA RAY ZR 125 (2026)
F25: =D25*3% -> 0 | G25: =D25-F25 -> 0 | J25: =D25*5% -> 0 | K25: =D25-J25 -> 0
A26: 11 | B26: XC115BNS | C26: CYGNUS RAY ZR 2025 | D26: 40525 | E26: 38499 | F26: =D26*3% -> 1215.75 | G26: =D26-F26 -> 39309.25 | J26: =D26*5% -> 2026.25 | K26: =D26-J26 -> 38498.75 | L26: MOTONETA CYGNUS RAY ZR (2025)
A28: 12 | B28: XC115BNT | C28: CYGNUS RAY ZR (2026) | D28: 41052 | E28: 38999 | F28: =D28*3% -> 1231.56 | G28: =D28-F28 -> 39820.44 | J28: =D28*5% -> 2052.6 | K28: =D28-J28 -> 38999.4 | L28: MOTONETA CYGNUS RAY ZR (2026) | M28: CON BONO 1,000.00 | O28: 37999
B29: TRABAJO | F29: =D29*3% -> 0 | G29: =D29-F29 -> 0 | J29: =D29*5% -> 0 | K29: =D29-J29 -> 0
A30: 13 | B30: YB125ZR | C30: YBR 125ZR (2026) | D30: 46315 | E30: 43999 | F30: =D30*3% -> 1389.45 | G30: =D30-F30 -> 44925.55 | J30: =D30*5% -> 2315.75 | K30: =D30-J30 -> 43999.25 | L30: MOTOCICLETA YBR 125ZR (2026)
F31: =D31*3% -> 0 | G31: =D31-F31 -> 0 | H31: MANO DE OBRA GRATIS EN 2° SERVICIO | I31: MANO DE OBRA GRATIS EN 2° SERVICIO | J31: =D31*5% -> 0 | K31: =D31-J31 -> 0
A32: 14 | B32: YB125BR | C32: YB 125 (2026) | D32: 39999 | E32: 37999 | F32: =D32*3% -> 1199.97 | G32: =D32-F32 -> 38799.03 | I32: 1AÑO SERVICIO o 5 SERVICIOS | J32: =D32*5% -> 1999.95 | K32: =D32-J32 -> 37999.05 | L32: MOTOCICLETA YB 125 (2026)
H33: MANO DE OBRA GRATIS EN 2° SERVICIO | I33: MANO DE OBRA GRATIS EN 2° SERVICIO
A34: 15 | B34: YBR125CBS | C34: YBR 125C EXPRESS (2025) | D34: 41052 | E34: 38999 | F34: =D34*3% -> 1231.56 | G34: =D34-F34 -> 39820.44 | J34: =D34*5% -> 2052.6 | K34: =D34-J34 -> 38999.4 | L34: MOTOCICLETA YBR 125C EXPRESS (2025)
H35: MANO DE OBRA GRATIS EN 2° SERVICIO | I35: MANO DE OBRA GRATIS EN 2° SERVICIO
A36: 16 | B36: YBR125CBS | C36: YBR 125C EXPRESS (2026) | D36: 41052 | E36: 38999 | F36: =D36*3% -> 1231.56 | G36: =D36-F36 -> 39820.44 | I36: 1AÑO SERVICIO o 5 SERVICIOS | J36: =D36*5% -> 2052.6 | K36: =D36-J36 -> 38999.4 | L36: MOTOCICLETA YBR 125C EXPRESS (2026) | M36: CON BONO 2,000.00 | O36: 36999
H37: MANO DE OBRA GRATIS EN 2° SERVICIO | I37: MANO DE OBRA GRATIS EN 2° SERVICIO
A38: 17 | B38: T115CBT | C38: CRYPTON 115 FI (2026) | D38: 37894 | E38: 35999 | F38: =D38*3% -> 1136.82 | G38: =D38-F38 -> 36757.18 | J38: =D38*5% -> 1894.7 | K38: =D38-J38 -> 35999.3 | L38: MOTOCICLETA CRYPTON 115 FI (2026)
B39: STREET | F39: =D39*3% -> 0 | G39: =D39-F39 -> 0 | J39: =D39*5% -> 0 | K39: =D39-J39 -> 0
A40: 18 | B40: FZSV2BT | C40: FZ S VERSION 2.0 2026 | D40: 59999 | E40: 56999 | F40: =D40*3% -> 1799.97 | G40: =D40-F40 -> 58199.03 | J40: =D40*5% -> 2999.95 | K40: =D40-J40 -> 56999.05 | L40: MOTOCICLETA FZ S VERSION 2.0 2026 | M40: CON BONO | O40: 54999
A42: 19 | B42: FZSBT | C42: FZ S VERSION 3.0 2026 | D42: 66315 | E42: 62999 | F42: =D42*3% -> 1989.45 | G42: =D42-F42 -> 64325.55 | J42: =D42*5% -> 3315.75 | K42: =D42-J42 -> 62999.25 | L42: MOTOCICLETA FZ VERSION 3.0 2026
A44: 20 | B44: FZSBR | C44: FZ S V 4.0 ABS (2025) | D44: 70525 | E44: 66999 | F44: =D44*3% -> 2115.75 | G44: =D44-F44 -> 68409.25 | J44: =D44*5% -> 3526.25 | K44: =D44-J44 -> 66998.75 | L44: MOTOCICLETA FZ S V 4.0 ABS (2025)
A46: 21 | B46: FZSBR | C46: FZ S V 4.0 ABS (2026) | D46: 71578 | E46: 67999 | F46: =D46*3% -> 2147.34 | G46: =D46-F46 -> 69430.66 | J46: =D46*5% -> 3578.9 | K46: =D46-J46 -> 67999.1 | L46: MOTOCICLETA FZ S V 4.0 ABS (2026)
A48: 22 | B48: FZ25BS6 | C48: FZ 25 ABS NUEVA (2025) | D48: 93683 | E48: 88999 | F48: =D48*3% -> 2810.49 | G48: =D48-F48 -> 90872.51 | J48: =D48*5% -> 4684.15 | K48: =D48-J48 -> 88998.85 | L48: MOTOCICLETA FZ 25 NUEVA (2025)
A50: 23 | B50: FZ25BS6 | C50: FZ 25 ABS NUEVA (2026 | D50: 94736 | E50: 89999 | F50: =D50*3% -> 2842.08 | G50: =D50-F50 -> 91893.92 | J50: =D50*5% -> 4736.8 | K50: =D50-J50 -> 89999.2 | L50: MOTOCICLETA FZ 25 NUEVA (2026)
A52: 24 | B52: FZ25BS | C52: FZ 25 ABS (2025) | D52: 91578 | E52: 86999 | F52: =D52*3% -> 2747.34 | G52: =D52-F52 -> 88830.66 | J52: =D52*5% -> 4578.9 | K52: =D52-J52 -> 86999.1 | L52: MOTOCICLETA FZ 25 (2025)
A54: 25
B55: DEPORTIVAS | F55: =D55*3% -> 0 | G55: =D55-F55 -> 0 | J55: =D55*5% -> 0 | K55: =D55-J55 -> 0
A56: 26 | B56: MTN155BS | C56: MT 15 (2025) | D56: 102105 | E56: 96999 | F56: =D56*3% -> 3063.15 | G56: =D56-F56 -> 99041.85 | J56: =D56*5% -> 5105.25 | K56: =D56-J56 -> 96999.75 | L56: MOTOCICLETA MT 15 (2025)
A57: 27 | B57: MTN155BT | C57: MT 15 (2026) | D57: 103157 | E57: 97999 | F57: =D57*3% -> 3094.71 | G57: =D57-F57 -> 100062.29 | J57: =D57*5% -> 5157.85 | K57: =D57-J57 -> 97999.15 | L57: MOTOCICLETA MT 15 (2026)
A58: 28 | B58: MTN320BT | C58: MT 03 ABS (2025) | D58: 164210 | E58: 155999 | F58: =D58*3% -> 4926.3 | G58: =D58-F58 -> 159283.7 | J58: =D58*5% -> 8210.5 | K58: =D58-J58 -> 155999.5 | L58: MOTOCICLETA MT 03 (2025)
A60: 29 | B60: MTN320BS | C60: MT 03 ABS (2026) | D60: 165262 | E60: 156999 | F60: =D60*3% -> 4957.86 | G60: =D60-F60 -> 160304.14 | J60: =D60*5% -> 8263.1 | K60: =D60-J60 -> 156998.9 | L60: MOTOCICLETA MT 03 (2026)
A62: 30 | B62: MTN69U1S | C62: MT 07 (2025) | D62: 273684 | E62: 259999 | F62: =D62*3% -> 8210.52 | G62: =D62-F62 -> 265473.48 | J62: =D62*5% -> 13684.2 | K62: =D62-J62 -> 259999.8 | L62: MOTOCICLETA MT 07 (2025)
F63: =D63*3% -> 0 | G63: =D63-F63 -> 0 | J63: =D63*5% -> 0 | K63: =D63-J63 -> 0
A64: 31 | B64: MTN69U1T | C64: MT 07 (2026) | D64: 278946 | E64: 264999 | F64: =D64*3% -> 8368.38 | G64: =D64-F64 -> 270577.62 | J64: =D64*5% -> 13947.3 | K64: =D64-J64 -> 264998.7 | L64: MOTOCICLETA MT 07 (2026)
F65: =D65*3% -> 0 | G65: =D65-F65 -> 0 | J65: =D65*5% -> 0 | K65: =D65-J65 -> 0
A66: 32 | B66: MT9AU9S | C66: MT 09 (2025) | D66: 321052 | E66: 304999 | F66: =D66*3% -> 9631.56 | G66: =D66-F66 -> 311420.44 | J66: =D66*5% -> 16052.6 | K66: =D66-J66 -> 304999.4 | L66: MOTOCICLETA MT 09 (2025)
A68: 33 | B68: MT9AU9T | C68: MT 09 (2026) | D68: 326315 | E68: 309999 | F68: =D68*3% -> 9789.45 | G68: =D68-F68 -> 316525.55 | J68: =D68*5% -> 16315.75 | K68: =D68-J68 -> 309999.25 | L68: MOTOCICLETA MT 09 (2026)
B69: SUPER DEPORTIVAS | F69: =D69*3% -> 0 | G69: =D69-F69 -> 0 | J69: =D69*5% -> 0 | K69: =D69-J69 -> 0
A70: 34 | B70: YZFR15BT | C70: YZF R15 V.4.0 (2026) | D70: 108420 | E70: 102999 | F70: =D70*3% -> 3252.6 | G70: =D70-F70 -> 105167.4 | J70: =D70*5% -> 5421 | K70: =D70-J70 -> 102999 | L70: MOTOCICLETA YZF R15 V.4.0 (2026)
A72: 35 | B72: YZFR15BS | C72: YZF R15 V.4.0 (2025) | D72: 107368 | E72: 101999 | F72: =D72*3% -> 3221.04 | G72: =D72-F72 -> 104146.96 | J72: =D72*5% -> 5368.4 | K72: =D72-J72 -> 101999.6 | L72: MOTOCICLETA YZF R15 V.4.0 (2025)
F73: =D73*3% -> 0 | G73: =D73-F73 -> 0
A74: 36 | B74: YZFR9BT | C74: YZF R9 (2026) | D74: 378947 | E74: 359999 | F74: =D74*3% -> 11368.41 | G74: =D74-F74 -> 367578.59 | J74: =D74*5% -> 18947.35 | K74: =D74-J74 -> 359999.65 | L74: MOTOCICLETA YZF R9 (2026) | M74: CON BONO 30,000.00 | O74: 329999
A76: 37 | B76: YZFR3BT | C76: YZF R-3 (2026) | D76: 168420 | E76: 159999 | F76: =D76*3% -> 5052.6 | G76: =D76-F76 -> 163367.4 | J76: =D76*5% -> 8421 | K76: =D76-J76 -> 159999 | L76: MOTOCICLETA YZFR-3 (2026)
F77: =D77*3% -> 0 | G77: =D77-F77 -> 0
A78: 38 | B78: YZFR1SCUM | C78: YZF-R1 (2026) | D78: 568420 | E78: 539999 | F78: =D78*3% -> 17052.6 | G78: =D78-F78 -> 551367.4 | J78: =D78*5% -> 28421 | K78: =D78-J78 -> 539999 | L78: MOTOCICLETA YZF-R1 (2026)
A80: 39 | B80: YZF69Z | C80: YZF R7 (2026) | D80: 289473 | E80: 274999 | F80: =D80*3% -> 8684.19 | G80: =D80-F80 -> 280788.81 | J80: =D80*5% -> 14473.65 | K80: =D80-J80 -> 274999.35 | L80: MOTOCICLETA YZF R7 (2026) | M80: CON BONO 15,000.00 | O80: 259999
B83: CRUCERO | F83: =D83*3% -> 0 | G83: =D83-F83 -> 0 | J83: =D83*5% -> 0 | K83: =D83-J83 -> 0
B85: DOBLE PROPOSITO | F85: =D85*3% -> 0 | G85: =D85-F85 -> 0 | J85: =D85*5% -> 0 | K85: =D85-J85 -> 0
A86: 41 | B86: YBR125EGBRS | C86: YBR 125G 2025 | D86: 51052 | E86: 48499 | F86: =D86*3% -> 1531.56 | G86: =D86-F86 -> 49520.44 | J86: =D86*5% -> 2552.6 | K86: =D86-J86 -> 48499.4 | L86: MOTOCICLETA YBR 125G 2025 | M86: BONO 2,000.00 | O86: 46499
A88: 42 | B88: YBR125EGBRS | C88: YBR 125G 2026 | D88: 51578 | E88: 48999 | F88: =D88*3% -> 1547.34 | G88: =D88-F88 -> 50030.66 | J88: =D88*5% -> 2578.9 | K88: =D88-J88 -> 48999.1 | L88: MOTOCICLETA YBR 125G 2026 | M88: BONO 2,000.00 | O88: 46999
F89: =D89*3% -> 0 | G89: =D89-F89 -> 0 | J89: =D89*5% -> 0 | K89: =D89-J89 -> 0
A90: 43 | B90: XTZ125EBS | C90: XTZ 125E 2025 | D90: 53157 | E90: 50499 | F90: =D90*3% -> 1594.71 | G90: =D90-F90 -> 51562.29 | J90: =D90*5% -> 2657.85 | K90: =D90-J90 -> 50499.15 | L90: MOTOCICLETA XTZ 125E 2025 | M90: BONO 2,000.00 | O90: 48499
A92: 44 | B92: XTZ125EBS | C92: XTZ 125E 2026 | D92: 53157 | E92: 50499 | F92: =D92*3% -> 1594.71 | G92: =D92-F92 -> 51562.29 | J92: =D92*5% -> 2657.85 | K92: =D92-J92 -> 50499.15 | L92: MOTOCICLETA XTZ 125E 2026 | M92: BONO 1,500.00 | O92: 48999
A94: 45 | B94: XTZ150EBS | C94: XTZ 150 2025 | D94: 69999 | E94: 66499 | F94: =D94*3% -> 2099.97 | G94: =D94-F94 -> 67899.03 | J94: =D94*5% -> 3499.95 | K94: =D94-J94 -> 66499.05 | L94: MOTOCICLETA XTZ 150 2025
A96: 46 | B96: XTZ150EBT | C96: XTZ 150 2026 | D96: 70526 | E96: 66999 | F96: =D96*3% -> 2115.78 | G96: =D96-F96 -> 68410.22 | J96: =D96*5% -> 3526.3 | K96: =D96-J96 -> 66999.7 | L96: MOTOCICLETA XTZ 150 2026
J97: =D97*5% -> 0 | K97: =D97-J97 -> 0
A98: 47 | C98: TRACER 9 GT | D98: 421052 | E98: 399999 | J98: =D98*5% -> 21052.6 | K98: =D98-J98 -> 399999.4 | L98: MOTOCICLETA TRACER 9 GT
J99: =D99*5% -> 0
A100: 48 | B100: TENERE700 | C100: Tenere 700 (2026) | D100: 357894 | E100: 339999 | F100: =D100*3% -> 10736.82 | G100: =D100-F100 -> 347157.18 | J100: =D100*5% -> 17894.7 | K100: =D100-J100 -> 339999.3 | L100: MOTOCICLETA Tenere 700 (2026)
F101: =D101*3% -> 0 | G101: =D101-F101 -> 0 | J101: =D101*5% -> 0 | K101: =D101-J101 -> 0
A102: 49 | B102: XT12UM | C102: Super Tenere 1200Z (2024) | D102: 442104.5 | E102: 419999 | F102: =D102*3% -> 13263.135 | G102: =D102-F102 -> 428841.36 | J102: =D102*5% -> 22105.225 | K102: =D102-J102 -> 419999.28 | L102: MOTOCICLETA Super Tenere 1200 Z (2024)
B103: OFF ROAD | F103: =D103*3% -> 0 | G103: =D103-F103 -> 0 | J103: =D103*5% -> 0 | K103: =D103-J103 -> 0
A104: 51 | B104: PW50FS | C104: PW50 (2025) | D104: 59999 | E104: 56999 | F104: =D104*3% -> 1799.97 | G104: =D104-F104 -> 58199.03 | J104: =D104*5% -> 2999.95 | K104: =D104-J104 -> 56999.05 | L104: MOTOCICLETA PW50 2025
I105: PROMOCION DEL MES: CASCO DE REGALO
A106: 52 | B106: YZ85LWF5 | C106: YZ85 (2024) | D106: 149473 | E106: 141999 | F106: =D106*3% -> 4484.19 | G106: 141999 | I106: RIGUROSO CONTADO 128,000.00 | J106: =D106*5% -> 7473.65 | K106: =D106-J106 -> 141999.35 | L106: MOTOCICLETA YZ 85 (2024) | O106: 128000
F107: =D107*3% -> 0 | G107: =D107-F107 -> 0 | I107: PROMOCION DEL MES: CASCO DE REGALO | J107: =D107*5% -> 0 | K107: =D107-J107 -> 0
A108: 53 | B108: YZ85LWF6 | C108: YZ85 (2026) | D108: 149473 | E108: 141999 | F108: =D108*3% -> 4484.19 | G108: =D108-F108 -> 144988.81 | J108: =D108*5% -> 7473.65 | K108: =D108-J108 -> 141999.35 | L108: MOTOCICLETA YZ 85 (2026)
F109: =D109*3% -> 0 | G109: =D109-F109 -> 0 | I109: PROMOCION DEL MES: CASCO DE REGALO | J109: =D109*5% -> 0 | K109: =D109-J109 -> 0
A110: 54 | B110: YZ125BP | C110: YZ 125 (2024) | D110: 198947 | E110: 188999 | F110: =D110*3% -> 5968.41 | G110: 188999 | I110: RIGUROSO CONTADO 170,000.00 | J110: =D110*5% -> 9947.35 | K110: =D110-J110 -> 188999.65 | L110: MOTOCICLETA YZ 125 (2024) | O110: 170000
I111: PROMOCION DEL MES: CASCO DE REGALO
A112: 55 | B112: YZ65BP | C112: YZ 65 | D112: 127367 | E112: 120999 | F112: =D112*3% -> 3821.01 | G112: =D112-F112 -> 123545.99 | J112: =D112*5% -> 6368.35 | K112: =D112-J112 -> 120998.65 | L112: MOTOCICLETA YZ 65 (2026)
A114: 56 | B114: YZ250FF3 | C114: YZ250F 2025 | D114: 236841 | E114: 224999 | F114: =D114*3% -> 7105.23 | G114: =D114-F114 -> 229735.77 | J114: =D114*5% -> 11842.05 | K114: =D114-J114 -> 224998.95 | L114: MOTOCICLETA YZ250F 2025
F115: =D115*3% -> 0 | G115: =D115-F115 -> 0 | J115: =D115*5% -> 0 | K115: =D115-J115 -> 0
A116: 57 | B116: YZ250FF3 | C116: YZ250F 2026 | D116: 236841 | E116: 224999 | F116: =D116*3% -> 7105.23 | G116: =D116-F116 -> 229735.77 | J116: =D116*5% -> 11842.05 | K116: =D116-J116 -> 224998.95 | L116: MOTOCICLETA YZ250F 2026
A118: 58 | B118: YZ250FXOM | C118: YZ250FX (2025) | D118: 242104 | E118: 229999 | F118: =D118*3% -> 7263.12 | G118: =D118-F118 -> 234840.88 | J118: =D118*5% -> 12105.2 | K118: =D118-J118 -> 229998.8 | L118: MOTOCICLETA YZ250FX (2025) | M118: BONO 30,000.00 | O118: 199999
F119: =D119*3% -> 0 | G119: =D119-F119 -> 0 | J119: =D119*5% -> 0 | K119: =D119-J119 -> 0
A120: 59 | B120: YZ450FF2 | C120: YZ450F 2026 | D120: 242104 | E120: 229999 | F120: =D120*3% -> 7263.12 | G120: =D120-F120 -> 234840.88 | J120: =D120*5% -> 12105.2 | K120: =D120-J120 -> 229998.8 | L120: MOTOCICLETA YZ450F (2026)
F121: =D121*3% -> 0 | G121: =D121-F121 -> 0 | J121: =D121*5% -> 0 | K121: =D121-J121 -> 0
A122: 60 | B122: YZ450FXO2 | C122: YZ450FX 2025 | D122: 242104 | E122: 229999 | F122: =D122*3% -> 7263.12 | G122: =D122-F122 -> 234840.88 | J122: =D122*5% -> 12105.2 | K122: =D122-J122 -> 229998.8 | L122: MOTOCICLETA YZ450FX (2025) | M122: BONO 20,000.00 | O122: 209999
B123: ATV Utilitario | F123: =D123*3% -> 0 | G123: =D123-F123 -> 0 | J123: =D123*5% -> 0 | K123: =D123-J123 -> 0
A124: 61 | C124: KODIAK450 2024 | D124: 231578 | E124: 219999 | F124: =D124*3% -> 6947.34 | G124: =D124-F124 -> 224630.66 | K124: =D124-J124 -> 231578 | L124: KODIAK450 2024 | M124: BONO 30,000.00 | O124: 189999
A126: 62 | C126: KODIAK450 2025 | D126: 231578 | E126: 219999 | F126: =D126*3% -> 6947.34 | G126: =D126-F126 -> 224630.66 | K126: =D126-J126 -> 231578 | L126: KODIAK450 2025 | M126: BONO 30,000.00 | O126: 189999
F127: =D127*3% -> 0 | G127: =D127-F127 -> 0
A128: 63 | C128: KODIAK450 2026 | D128: 231578 | E128: 219999 | F128: =D128*3% -> 6947.34 | G128: =D128-F128 -> 224630.66 | K128: =D128-J128 -> 231578 | L128: KODIAK450 2026 | M128: BONO 20,000.00 | O128: 199999
F129: =D129*3% -> 0 | G129: =D129-F129 -> 0 | J129: =D129*5% -> 0 | K129: =D129-J129 -> 0
...

Sheet CREDITO2026
C4: Distribuidor Autorizado
C6: De Los Ángeles Motor´s
C7: Av. Reforma Sur #703 Col.Guadalupe Hidalgo Tehuacán, Pue.
C11: COTIZACION MOTOCICLETA YAMAHA
C14: CODIGO | D14: DESCRIPCION | I14: IMPORTE
C16: 14 | D16: =VLOOKUP(C16,CATALOGO_MOTOS!A6:L245,12) -> MOTOCICLETA YB 125 (2026) | I16: =VLOOKUP(C16,CATALOGO_MOTOS!A6:D245,4) -> 39999 | J16: =VLOOKUP(C16,CATALOGO_MOTOS!A6:M245,13) -> 0
C18: 5 | D18: % Descuento Por Pago de Contado | I18: =VLOOKUP(C16,CATALOGO_MOTOS!A6:E245,5) -> 37999 | J18: =VLOOKUP(C16,CATALOGO_MOTOS!A6:O245,15) -> 0
C20: 3 | D20: % Descuento Por Pago a 3 meses | I20: =VLOOKUP(C16,CATALOGO_MOTOS!A6:G245,7) -> 38799.03
I22: =(I16-H23) -> 23999.4
D23: 0.4 | E23: % de Enganche | H23: =I16*D23 -> 15999.6
D25: 3 | E25: Mensualidades | H25: =(I20-H23)/3 -> 7599.81 | I25: =H23+(H25*D25) -> 38799.03
D27: 6 | E27: Mensulaidades | H27: =(I22*12%+I22)/6 -> 4479.888 | I27: =H23+(H27*D27) -> 42878.928 | J27: =I27-I16 -> 2879.928
D29: 8 | E29: Mensualidades | H29: =(I22*16%+I22)/8 -> 3479.913 | I29: =H23+(H29*D29) -> 43838.904 | J29: =I29-I16 -> 3839.904
D33: PROMOCION DURANTE EL MES:
D34: PROMOCION DEL MES : | H34: =VLOOKUP(C16,CATALOGO_MOTOS!A6:I245,9) -> 1AÑO SERVICIO o 5 SERVICIOS
D37: REQUISITOS PARA CREDITO:
C38: 1. Credencial INE original vigente.
C39: 2. CURP.
C40: 3. Número de telefono | J40: (SE QUEDAN COPIAS)
C41: 4. Correo Electronico.
C42: 5. Comprobante de domicilio original no mayor a tres meses
C43: 6. Garantía que cubra el total del crédito solicitado, más un 30% adicional como respaldo.
C44: a) Escritura de propiedad con predial pagado y carta libre de gravamen.
C45: b) Factura de automovil o motocicleta endosada junto con tarjeta de circulación vigente
C48: Requisitos para métodos fiscales (si el cliente solicita factura para persona física o moral)
C49: • Alta de hacienda, RFC, hoja de situacion fiscal o formato 32-D
C50: • Acta constitutiva o nombramiento de representante legal
C51: • Constancia de situacion fiscal
C52: • 1 Estado de cuenta bancarios
D55: ATENDIDO POR: | G55: ANA MARIA CEPEDA BARROSO
D57: FECHA DE EMISION: | G57: =TEXT(TODAY(),"d \d\e mmmm \d\e aaaa") -> 7 de agosto de 2026
C60: En la compra de tu motocicleta, recibe un bono de $500.00 o
C61: un segundo servicio gratuito (solo mano de obra, no incluye insumos)
C62: Consulta la promoción que aplica este mes.
F64: www.yamaha-motor.com.mx
C67: N O T A S :
C68: * Incluye el 2% de interes Mensual *
C69: En caso de que el solicitante no cuente con una garantia, este debe contar con aval
C70: El Aval debe cumplir con los requisitos para credito (1 al 6).
C71: Facturas en garantía, incluida la de la moto, deben entregarse endosadas (firmadas al reverso). | L71: ANA MARIA CEPEDA BARROSO | M71: Casco de regalo
C72: COTIZACION VALIDA 5 DIAS HABILES A PARTIR DE LA FECHA DE EMISION | L72: MARISOL RODRIGUEZ SANTIAGO | M72: 2° Servicio Gratuito
I74: 2382000456
